<?xml version="1.0"?>

<!DOCTYPE hibernate-mapping PUBLIC "-//Hibernate/Hibernate Mapping DTD 3.0//EN" "http://hibernate.sourceforge.net/hibernate-mapping-3.0.dtd">

<hibernate-mapping package="org.archiviststoolkit.model">

	<class name="LookupListItems"
		   table="LookupListItems"
		   lazy="false">

		<!-- Common id property. -->
		<id name="lookupListItemId" column="lookupListItemId" type="java.lang.Long">
			<generator class="native"></generator>
		</id>

		<version name="version" type="java.lang.Long" column="version"/>

        <property name="auditInfo" type="org.archiviststoolkit.hibernate.AuditInfoType">
            <column name="lastUpdated"/>
            <column name="created"/>
            <column name="lastUpdatedBy"/>
            <column name="createdBy"/>
        </property>

		<property name="listItem"
				  column="listItem"
				  type="string"
				  not-null="true"/>

		<property name="code"
				  column="code"
				  type="string"/>

		<property name="editable"
				  column="editable"
				  type="boolean"
				  not-null="true"/>

		<property name="atInitialValue"
				  column="atInitialValue"
				  type="boolean"
				  not-null="true"/>


		<many-to-one name="lookUpList"
					 class="org.archiviststoolkit.model.LookupList"
					 column="lookupListId"
					 access="field"
					 fetch="join"
					 outer-join="true"/>
	</class>

</hibernate-mapping>